cloudscript/__init__.py
cloudscript/constants.py
cloudscript-0.0.1.dist-info/LICENSE.txt
cloudscript-0.0.1.dist-info/METADATA
cloudscript-0.0.1.dist-info/WHEEL
cloudscript-0.0.1.dist-info/entry_points.txt
cloudscript-0.0.1.dist-info/top_level.txt
cloudscript-0.0.1.dist-info/RECORD
