Metadata-Version: 2.1
Name: cloudscript
Version: 0.0.1
Summary: Implementation of the cloudscript specification in python.
Home-page: https://github.com/simonski/cloudscript
Author: Simon Gauld
Author-email: simon.gauld@gmail.com
License: Apache 2.0
Keywords: cloud infrastructure common development
Platform: UNKNOWN
Classifier: Development Status :: 3 - Alpha
Requires-Dist: adal (==1.2.2)
Requires-Dist: azure (==4.0.0)
Requires-Dist: azure-applicationinsights (==0.1.0)
Requires-Dist: azure-batch (==4.1.3)
Requires-Dist: azure-common (==1.1.23)
Requires-Dist: azure-cosmosdb-nspkg (==2.0.2)
Requires-Dist: azure-cosmosdb-table (==1.0.6)
Requires-Dist: azure-datalake-store (==0.0.48)
Requires-Dist: azure-eventgrid (==1.3.0)
Requires-Dist: azure-graphrbac (==0.40.0)
Requires-Dist: azure-keyvault (==1.1.0)
Requires-Dist: azure-loganalytics (==0.1.0)
Requires-Dist: azure-mgmt (==4.0.0)
Requires-Dist: azure-mgmt-advisor (==1.0.1)
Requires-Dist: azure-mgmt-applicationinsights (==0.1.1)
Requires-Dist: azure-mgmt-authorization (==0.50.0)
Requires-Dist: azure-mgmt-batch (==5.0.1)
Requires-Dist: azure-mgmt-batchai (==2.0.0)
Requires-Dist: azure-mgmt-billing (==0.2.0)
Requires-Dist: azure-mgmt-cdn (==3.1.0)
Requires-Dist: azure-mgmt-cognitiveservices (==3.0.0)
Requires-Dist: azure-mgmt-commerce (==1.0.1)
Requires-Dist: azure-mgmt-compute (==4.6.2)
Requires-Dist: azure-mgmt-consumption (==2.0.0)
Requires-Dist: azure-mgmt-containerinstance (==1.5.0)
Requires-Dist: azure-mgmt-containerregistry (==2.8.0)
Requires-Dist: azure-mgmt-containerservice (==4.4.0)
Requires-Dist: azure-mgmt-cosmosdb (==0.4.1)
Requires-Dist: azure-mgmt-datafactory (==0.6.0)
Requires-Dist: azure-mgmt-datalake-analytics (==0.6.0)
Requires-Dist: azure-mgmt-datalake-nspkg (==3.0.1)
Requires-Dist: azure-mgmt-datalake-store (==0.5.0)
Requires-Dist: azure-mgmt-datamigration (==1.0.0)
Requires-Dist: azure-mgmt-devspaces (==0.1.0)
Requires-Dist: azure-mgmt-devtestlabs (==2.2.0)
Requires-Dist: azure-mgmt-dns (==2.1.0)
Requires-Dist: azure-mgmt-eventgrid (==1.0.0)
Requires-Dist: azure-mgmt-eventhub (==2.6.0)
Requires-Dist: azure-mgmt-hanaonazure (==0.1.1)
Requires-Dist: azure-mgmt-iotcentral (==0.1.0)
Requires-Dist: azure-mgmt-iothub (==0.5.0)
Requires-Dist: azure-mgmt-iothubprovisioningservices (==0.2.0)
Requires-Dist: azure-mgmt-keyvault (==1.1.0)
Requires-Dist: azure-mgmt-loganalytics (==0.2.0)
Requires-Dist: azure-mgmt-logic (==3.0.0)
Requires-Dist: azure-mgmt-machinelearningcompute (==0.4.1)
Requires-Dist: azure-mgmt-managementgroups (==0.1.0)
Requires-Dist: azure-mgmt-managementpartner (==0.1.1)
Requires-Dist: azure-mgmt-maps (==0.1.0)
Requires-Dist: azure-mgmt-marketplaceordering (==0.1.0)
Requires-Dist: azure-mgmt-media (==1.0.0)
Requires-Dist: azure-mgmt-monitor (==0.5.2)
Requires-Dist: azure-mgmt-msi (==0.2.0)
Requires-Dist: azure-mgmt-network (==2.7.0)
Requires-Dist: azure-mgmt-notificationhubs (==2.1.0)
Requires-Dist: azure-mgmt-nspkg (==3.0.2)
Requires-Dist: azure-mgmt-policyinsights (==0.1.0)
Requires-Dist: azure-mgmt-powerbiembedded (==2.0.0)
Requires-Dist: azure-mgmt-rdbms (==1.9.0)
Requires-Dist: azure-mgmt-recoveryservices (==0.3.0)
Requires-Dist: azure-mgmt-recoveryservicesbackup (==0.3.0)
Requires-Dist: azure-mgmt-redis (==5.0.0)
Requires-Dist: azure-mgmt-relay (==0.1.0)
Requires-Dist: azure-mgmt-reservations (==0.2.1)
Requires-Dist: azure-mgmt-resource (==2.2.0)
Requires-Dist: azure-mgmt-scheduler (==2.0.0)
Requires-Dist: azure-mgmt-search (==2.1.0)
Requires-Dist: azure-mgmt-servicebus (==0.5.3)
Requires-Dist: azure-mgmt-servicefabric (==0.2.0)
Requires-Dist: azure-mgmt-signalr (==0.1.1)
Requires-Dist: azure-mgmt-sql (==0.9.1)
Requires-Dist: azure-mgmt-storage (==2.0.0)
Requires-Dist: azure-mgmt-subscription (==0.2.0)
Requires-Dist: azure-mgmt-trafficmanager (==0.50.0)
Requires-Dist: azure-mgmt-web (==0.35.0)
Requires-Dist: azure-nspkg (==3.0.2)
Requires-Dist: azure-servicebus (==0.21.1)
Requires-Dist: azure-servicefabric (==6.3.0.0)
Requires-Dist: azure-servicemanagement-legacy (==0.20.6)
Requires-Dist: azure-storage-blob (==1.5.0)
Requires-Dist: azure-storage-common (==1.4.2)
Requires-Dist: azure-storage-file (==1.4.0)
Requires-Dist: azure-storage-queue (==1.4.0)
Requires-Dist: bleach (==3.1.0)
Requires-Dist: boto3 (==1.10.14)
Requires-Dist: botocore (==1.13.14)
Requires-Dist: certifi (==2019.9.11)
Requires-Dist: cffi (==1.13.2)
Requires-Dist: chardet (==3.0.4)
Requires-Dist: cryptography (==2.8)
Requires-Dist: docutils (==0.15.2)
Requires-Dist: gcloud (==0.18.3)
Requires-Dist: googleapis-common-protos (==1.6.0)
Requires-Dist: httplib2 (==0.14.0)
Requires-Dist: idna (==2.8)
Requires-Dist: isodate (==0.6.0)
Requires-Dist: jmespath (==0.9.4)
Requires-Dist: msrest (==0.6.10)
Requires-Dist: msrestazure (==0.6.2)
Requires-Dist: oauth2client (==4.1.3)
Requires-Dist: oauthlib (==3.1.0)
Requires-Dist: pkginfo (==1.5.0.1)
Requires-Dist: protobuf (==3.10.0)
Requires-Dist: pyasn1 (==0.4.7)
Requires-Dist: pyasn1-modules (==0.2.7)
Requires-Dist: pycparser (==2.19)
Requires-Dist: Pygments (==2.4.2)
Requires-Dist: PyJWT (==1.7.1)
Requires-Dist: python-dateutil (==2.8.0)
Requires-Dist: readme-renderer (==24.0)
Requires-Dist: requests (==2.22.0)
Requires-Dist: requests-oauthlib (==1.3.0)
Requires-Dist: requests-toolbelt (==0.9.1)
Requires-Dist: rsa (==4.0)
Requires-Dist: s3transfer (==0.2.1)
Requires-Dist: six (==1.13.0)
Requires-Dist: tqdm (==4.38.0)
Requires-Dist: twine (==2.0.0)
Requires-Dist: urllib3 (==1.25.6)
Requires-Dist: webencodings (==0.5.1)
